pygifconvt_jsm/__init__.py
pygifconvt_jsm/converter.py
pygifconvt_jsm-1.0.1.dist-info/LICENSE
pygifconvt_jsm-1.0.1.dist-info/METADATA
pygifconvt_jsm-1.0.1.dist-info/WHEEL
pygifconvt_jsm-1.0.1.dist-info/top_level.txt
pygifconvt_jsm-1.0.1.dist-info/RECORD
